{
  "generator-jhipster": {
    "jhipsterVersion": "3.12.2",
    "baseName": "getdockerd",
    "packageName": "com.getdockerd",
    "packageFolder": "com/getdockerd",
    "serverPort": "8080",
    "authenticationType": "session",
    "hibernateCache": "ehcache",
    "clusteredHttpSession": false,
    "websocket": false,
    "databaseType": "sql",
    "devDatabaseType": "h2Disk",
    "prodDatabaseType": "postgresql",
    "searchEngine": "elasticsearch",
    "messageBroker": false,
    "buildTool": "maven",
    "enableSocialSignIn": false,
    "rememberMeKey": "17fc4888e98ae50ee576a7f08540ca18b624f32c",
    "useSass": false,
    "applicationType": "monolith",
    "testFrameworks": [
      "cucumber",
      "protractor"
    ],
    "jhiPrefix": "jhi",
    "enableTranslation": false
  }
}